matrixdemos/__init__.py
matrixdemos/__main__.py
matrixdemos/animations/cube/0001.png
matrixdemos/animations/cube/0002.png
matrixdemos/animations/cube/0003.png
matrixdemos/animations/cube/0004.png
matrixdemos/animations/cube/0005.png
matrixdemos/animations/cube/0006.png
matrixdemos/animations/cube/0007.png
matrixdemos/animations/cube/0008.png
matrixdemos/animations/cube/0009.png
matrixdemos/animations/cube/0010.png
matrixdemos/animations/cube/0011.png
matrixdemos/animations/cube/0012.png
matrixdemos/animations/cube/0013.png
matrixdemos/animations/cube/0014.png
matrixdemos/animations/cube/0015.png
matrixdemos/animations/cube/0016.png
matrixdemos/animations/cube/0017.png
matrixdemos/animations/cube/0018.png
matrixdemos/animations/cube/0019.png
matrixdemos/animations/cube/0020.png
matrixdemos/animations/cube/0021.png
matrixdemos/animations/cube/0022.png
matrixdemos/animations/cube/0023.png
matrixdemos/animations/cube/0024.png
matrixdemos/animations/cube/0025.png
matrixdemos/animations/cube/0026.png
matrixdemos/animations/cube/0027.png
matrixdemos/animations/cube/0028.png
matrixdemos/animations/cube/0029.png
matrixdemos/animations/cube/0030.png
matrixdemos/animations/cube/0031.png
matrixdemos/animations/cube/0032.png
matrixdemos/animations/cube/0033.png
matrixdemos/animations/cube/0034.png
matrixdemos/animations/cube/0035.png
matrixdemos/animations/cube/0036.png
matrixdemos/animations/cube/0037.png
matrixdemos/animations/cube/0038.png
matrixdemos/animations/cube/0039.png
matrixdemos/animations/cube/0040.png
matrixdemos/animations/cube/0041.png
matrixdemos/animations/cube/0042.png
matrixdemos/animations/cube/0043.png
matrixdemos/animations/cube/0044.png
matrixdemos/animations/cube/0045.png
matrixdemos/animations/cube/0046.png
matrixdemos/animations/cube/0047.png
matrixdemos/animations/cube/0048.png
matrixdemos/animations/cube/0049.png
matrixdemos/animations/cube/0050.png
matrixdemos/animations/cube/0051.png
matrixdemos/animations/cube/0052.png
MatrixDemos-0.3.dist-info/LICENSE
MatrixDemos-0.3.dist-info/METADATA
MatrixDemos-0.3.dist-info/WHEEL
MatrixDemos-0.3.dist-info/entry_points.txt
MatrixDemos-0.3.dist-info/top_level.txt
MatrixDemos-0.3.dist-info/RECORD
