Metadata-Version: 2.1
Name: MatrixDemos
Version: 0.3
Summary: A collection of demos for the Adafruit 32x32 matrix and a Raspberry Pi
Home-page: https://github.com/nachomonkey/MatrixDemos
Author: NachoMonkey
License: MIT
Platform: UNKNOWN
Classifier: Programming Language :: Python :: 3 :: Only
Classifier: Intended Audience :: Education
Classifier: Development Status :: 5 - Production/Stable
Classifier: Environment :: Console
Classifier: Natural Language :: English
Classifier: License :: OSI Approved :: MIT License
Classifier: Operating System :: POSIX :: Linux
Requires-Python: >=3.6
Requires-Dist: pillow
Requires-Dist: pygame
